weibo_api/__init__.py
weibo_api/async_client.py
weibo_api/client.py
weibo_api/config.py
weibo_api/connection_manager.py
weibo_api/dependency_container.py
weibo_api/exceptions.py
weibo_api/facade_client.py
weibo_api/mapper.py
weibo_api/metrics_collector.py
weibo_api/models.py
weibo_api/retry_manager.py
weibo_api/utils.py
weibo_api/examples/__init__.py
weibo_api/examples/advanced_usage.py
weibo_api/examples/async_usage.py
weibo_api/examples/basic_usage.py
weibo_api/examples/facade_pattern_demo.py
weibo_api_birkhoff-1.0.0.dist-info/METADATA
weibo_api_birkhoff-1.0.0.dist-info/WHEEL
weibo_api_birkhoff-1.0.0.dist-info/top_level.txt
weibo_api_birkhoff-1.0.0.dist-info/RECORD
